{
  "app": {
    "elm": {
      "development": { "debugger": true },
      "production": { "debugger": false }
    },
    "env": [],
    "html": {
      "attributes": {
        "html": { "lang": "en" },
        "head": {}
      },
      "title": "Elm Land",
      "meta": [
        { "charset": "UTF-8" },
        { "http-equiv": "X-UA-Compatible", "content": "IE=edge" },
        { "name": "viewport", "content": "width=device-width, initial-scale=1.0" }
      ],
      "link": [
        { "rel": "stylesheet", "href": "/dist/main.css" },
        { "rel": "apple-touch-icon", "sizes": "180x180", "href": "/apple-touch-icon.png" },
        { "rel": "icon", "type": "image/png", "sizes": "32x32", "href": "/favicon-32x32.png" },
        { "rel": "icon", "type": "image/png", "sizes": "16x16", "href": "/favicon-16x16.png" },
        { "rel": "manifest", "href": "/site.webmanifest" }
      ],
      "script": []
    },
    "router": {
      "useHashRouting": false
    }
  }
}
